[{"description":"A snackbar takes a queue of toasts and displays them to the user one after another.\nThey can be auto dismissed, or require user interaction to close the toast.","methods":[],"props":{"className":{"type":{"name":"string"},"required":false,"description":"An optional className to apply to the active toast."},"toasts":{"type":{"name":"arrayOf","value":{"name":"shape","value":{"text":{"name":"string","description":"The text to display in the toast.","required":true},"key":{"name":"any","description":"An optional key for the toast.","required":false},"action":{"name":"union","value":[{"name":"string"},{"name":"shape","value":{"onClick":{"name":"func","required":false},"label":{"name":"string","required":true}}}],"description":"An optional action to take. If this value is a string, a `FlatButton`\nwill be created with a `label` of this value and the `onClick` function\nwill be the `dismiss` function. If this is an object, all values will be\napplied to the `FlatButton`.","required":false},"onAppear":{"name":"func","description":"An optional function to call when the toast appears.","required":false}}}},"required":true,"description":"The moving queue of toasts to display.\n\n##### Shape Description","defaultValue":{"value":"[]","computed":false}},"autohide":{"type":{"name":"bool"},"required":false,"description":"Boolean if the toast should automatically hide after the given timeout.","defaultValue":{"value":"true","computed":false}},"autohideTimeout":{"type":{"name":"number"},"required":false,"description":"The auto hide timeout.","defaultValue":{"value":"3000","computed":false}},"dismiss":{"type":{"name":"func"},"required":true,"description":"A function to call that will dismiss the active toast."},"transitionName":{"type":{"name":"string"},"required":true,"description":"The transition name to use for the snackbar.","defaultValue":{"value":"'snackbar'","computed":false}},"transitionEnterTimeout":{"type":{"name":"number"},"required":true,"description":"The transition enter timeout for the snackbar.","defaultValue":{"value":"450","computed":false}},"transitionLeaveTimeout":{"type":{"name":"number"},"required":true,"description":"The transition leave timeout for the snackbar.","defaultValue":{"value":"450","computed":false}},"fab":{"type":{"name":"object"},"required":false,"description":"An optional Floating Action Button element that should be moved\nwhen a toast appears/disappears."}},"source":"src/js/Snackbars/Snackbar.js","component":"Snackbar"}]